{"WebRootFolder":"C:\\Users\\georg\\source\\repos\\XmasTreeLightsTo3D\\TreeLightsWeb\\wwwroot","LEDCount":560,"BlurAmount":5.0,"BrightnessThreshold":20.0,"MinPointsToKeep":40,"MaxYDiffBetweenTreeRotations":20,"ProportionToAssumeCorrectDistances":0.8,"ImageMaskingModels":[{"LeftBlank":128,"RightBlank":459},{"LeftBlank":105,"RightBlank":437},{"LeftBlank":105,"RightBlank":437},{"LeftBlank":105,"RightBlank":425},{"LeftBlank":83,"RightBlank":425},{"LeftBlank":83,"RightBlank":403},{"LeftBlank":128,"RightBlank":448},{"LeftBlank":128,"RightBlank":448}],"RecalculateImageLEDCoordinates":false}